py_cui/__init__.py
py_cui/colors.py
py_cui/debug.py
py_cui/errors.py
py_cui/grid.py
py_cui/keys.py
py_cui/popups.py
py_cui/renderer.py
py_cui/statusbar.py
py_cui/ui.py
py_cui/widget_set.py
py_cui/widgets.py
py_cui/controls/__init__.py
py_cui/controls/slider.py
py_cui/dialogs/__init__.py
py_cui/dialogs/filedialog.py
py_cui/dialogs/form.py
py_cui-0.1.4.dist-info/AUTHORS
py_cui-0.1.4.dist-info/LICENSE
py_cui-0.1.4.dist-info/METADATA
py_cui-0.1.4.dist-info/WHEEL
py_cui-0.1.4.dist-info/top_level.txt
py_cui-0.1.4.dist-info/RECORD
