Metadata-Version: 2.1
Name: py-cui
Version: 0.1.4
Summary: A widget and grid based framework for building command line user interfaces in python.
Home-page: https://github.com/jwlodek/py_cui
Author: Jakub Wlodek
Author-email: jwlodek.dev@gmail.com
License: BSD (3-clause)
Keywords: cui cli commandline user-interface ui
Platform: UNKNOWN
Classifier: Development Status :: 3 - Alpha
Classifier: Intended Audience :: Developers
Classifier: Programming Language :: Python :: 3.2
Classifier: Programming Language :: Python :: 3.3
Classifier: Programming Language :: Python :: 3.4
Classifier: Programming Language :: Python :: 3.5
Classifier: Programming Language :: Python :: 3.6
Classifier: Programming Language :: Python :: 3.7
Classifier: Programming Language :: Python :: 3.8
Requires-Python: >=3.6
